disnake_dyn_components/__init__.py
disnake_dyn_components/convertor.py
disnake_dyn_components/dyncomponents.py
disnake_dyn_components/components/DynButton.py
disnake_dyn_components/components/DynMenu.py
disnake_dyn_components/components/DynModal.py
disnake_dyn_components/components/__init__.py
disnake_dyn_components-0.2.3.dist-info/METADATA
disnake_dyn_components-0.2.3.dist-info/WHEEL
disnake_dyn_components-0.2.3.dist-info/top_level.txt
disnake_dyn_components-0.2.3.dist-info/RECORD
