Metadata-Version: 2.1
Name: disnake-dyn-components
Version: 0.2.3
Summary: Library for quick creation of ui components of discord with the ability to pass additional parameters
Home-page: https://github.com/NodusLorden/DisnakeDynComponents
Author: Lord_Nodus
Author-email: LordNodus@mail.ru
Keywords: example python
Classifier: Programming Language :: Python :: 3.12
Classifier: License :: OSI Approved :: MIT License
Classifier: Operating System :: OS Independent
Requires-Python: >=3.12
Requires-Dist: disnake>=2.10.1
